{
  "manifestVersion": "3.2",
  "proxies": [
    {
      "address": "0xC85022df8C414362Da3814770E449a74f150abfd",
      "txHash": "0x0e238aa76fa60241ef808c83c5237ca6c043224d3ac7559b5449a8042d97178c",
      "kind": "transparent"
    }
  ],
  "impls": {
    "472c056c09b2c2bba804837b8870cf765e7f0273c13567127dba807fe19ed08f": {
      "address": "0xAFe0820943ed13DB8036aD80df4E02677f959602",
      "txHash": "0x191bbb785bf0977af214007063f26bb565a2db6d6d639f9ee5f73ee1a11185af",
      "layout": {
        "solcVersion": "0.8.20",
        "storage": [
          {
            "label": "message",
            "offset": 0,
            "slot": "0",
            "type": "t_string_storage",
            "contract": "Swisstronik",
            "src": "contracts/Hello_swtr.sol:5"
          }
        ],
        "types": {
          "t_string_storage": {
            "label": "string",
            "numberOfBytes": "32"
          }
        },
        "namespaces": {}
      }
    }
  }
}
